pywerbi/__init__.py
pywerbi-0.0.1.dist-info/LICENSE
pywerbi-0.0.1.dist-info/METADATA
pywerbi-0.0.1.dist-info/WHEEL
pywerbi-0.0.1.dist-info/top_level.txt
pywerbi-0.0.1.dist-info/RECORD
